scte35/__init__.py
scte35/base.py
scte35/bitn.py
scte35/commands.py
scte35/crc.py
scte35/cue.py
scte35/descriptors.py
scte35/hls.py
scte35/packetdata.py
scte35/section.py
scte35/segment.py
scte35/segmentation.py
scte35/sixfix.py
scte35/spare.py
scte35/stream.py
scte35/streamtypes.py
scte35/sxp.py
scte35/upids.py
scte35/version.py
scte35/xml.py
scte35-0.0.17.data/scripts/scte35
scte35-0.0.17.dist-info/LICENSE
scte35-0.0.17.dist-info/METADATA
scte35-0.0.17.dist-info/WHEEL
scte35-0.0.17.dist-info/top_level.txt
scte35-0.0.17.dist-info/RECORD
