Metadata-Version: 2.1
Name: scte35
Version: 0.0.17
Summary: scte35 is a SCTE-35 Decoder and Encoder for MPEGTS, HLS and Everything else.
Home-page: https://github.com/superkabuki/scte35
Author: Adrian of Doom
Author-email: spam@iodisco.com
License: UNKNOWN
Platform: UNKNOWN
Classifier: License :: OSI Approved :: Sleepycat License
Classifier: Environment :: Console
Classifier: Operating System :: OS Independent
Classifier: Operating System :: POSIX :: BSD :: OpenBSD
Classifier: Operating System :: POSIX :: BSD :: NetBSD
Classifier: Operating System :: POSIX :: Linux
Classifier: Operating System :: POSIX :: SCO
Classifier: Operating System :: Unix
Classifier: Operating System :: Microsoft :: Windows :: Windows 3.1 or Earlier
Classifier: Operating System :: Other OS
Classifier: Topic :: Multimedia :: Video
Classifier: Programming Language :: Python :: 3.6
Classifier: Programming Language :: Python :: Implementation :: PyPy
Classifier: Programming Language :: Python :: Implementation :: CPython
Requires-Python: >=3.6
Requires-Dist: iframes (>=0.0.7)
Requires-Dist: m3ufu (>=0.0.89)
Requires-Dist: new-reader (>=0.1.11)
Requires-Dist: sideways (>=0.0.23)
Requires-Dist: pyaes
